odoo/addons/purchase_order_line_price_history/README.rst
odoo/addons/purchase_order_line_price_history/__init__.py
odoo/addons/purchase_order_line_price_history/__manifest__.py
odoo/addons/purchase_order_line_price_history/i18n/de.po
odoo/addons/purchase_order_line_price_history/i18n/es.po
odoo/addons/purchase_order_line_price_history/i18n/fr.po
odoo/addons/purchase_order_line_price_history/i18n/nl_NL.po
odoo/addons/purchase_order_line_price_history/i18n/purchase_order_line_price_history.pot
odoo/addons/purchase_order_line_price_history/readme/CONTRIBUTORS.rst
odoo/addons/purchase_order_line_price_history/readme/DESCRIPTION.rst
odoo/addons/purchase_order_line_price_history/readme/ROADMAP.rst
odoo/addons/purchase_order_line_price_history/readme/USAGE.rst
odoo/addons/purchase_order_line_price_history/security/ir.model.access.csv
odoo/addons/purchase_order_line_price_history/static/description/icon.png
odoo/addons/purchase_order_line_price_history/static/description/index.html
odoo/addons/purchase_order_line_price_history/tests/__init__.py
odoo/addons/purchase_order_line_price_history/tests/test_purchase_order_line_price_history.py
odoo/addons/purchase_order_line_price_history/views/purchase_views.xml
odoo/addons/purchase_order_line_price_history/wizards/__init__.py
odoo/addons/purchase_order_line_price_history/wizards/purchase_order_line_price_history.py
odoo/addons/purchase_order_line_price_history/wizards/purchase_order_line_price_history.xml
odoo14_addon_purchase_order_line_price_history-14.0.1.1.0.dist-info/METADATA
odoo14_addon_purchase_order_line_price_history-14.0.1.1.0.dist-info/WHEEL
odoo14_addon_purchase_order_line_price_history-14.0.1.1.0.dist-info/top_level.txt
odoo14_addon_purchase_order_line_price_history-14.0.1.1.0.dist-info/RECORD
